pycocotools/__init__.py
pycocotools/_mask.cpython-39-darwin.so
pycocotools/_mask.pyx
pycocotools/coco.py
pycocotools/cocoeval.py
pycocotools/mask.py
wf_pycocotools-2.0.1.4.dist-info/METADATA
wf_pycocotools-2.0.1.4.dist-info/WHEEL
wf_pycocotools-2.0.1.4.dist-info/top_level.txt
wf_pycocotools-2.0.1.4.dist-info/RECORD
